goldenkpg/__init__.py
goldenkpg/main.py
goldenkpg/templates/cpu_scheduling/README.txt
goldenkpg/templates/cpu_scheduling/fcfs.py
goldenkpg/templates/cpu_scheduling/priority.py
goldenkpg/templates/cpu_scheduling/priority_preemptive.py
goldenkpg/templates/cpu_scheduling/round_robin.py
goldenkpg/templates/cpu_scheduling/sjf.py
goldenkpg/templates/cpu_scheduling/srtf.py
goldenkpg/templates/disk_scheduling/README.txt
goldenkpg/templates/disk_scheduling/clook.py
goldenkpg/templates/disk_scheduling/cscan.py
goldenkpg/templates/disk_scheduling/fcfs.py
goldenkpg/templates/disk_scheduling/look.py
goldenkpg/templates/disk_scheduling/scan.py
goldenkpg/templates/disk_scheduling/sstf.py
goldenkpg/templates/memory_allocation/best_fit.py
goldenkpg/templates/memory_allocation/first_fit.py
goldenkpg/templates/memory_allocation/worst_fit.py
goldenkpg/templates/page_replacement/README.txt
goldenkpg/templates/page_replacement/clock.py
goldenkpg/templates/page_replacement/fifo.py
goldenkpg/templates/page_replacement/lru.py
goldenkpg/templates/page_replacement/optimal.py
goldenkpg-0.1.0.dist-info/METADATA
goldenkpg-0.1.0.dist-info/WHEEL
goldenkpg-0.1.0.dist-info/entry_points.txt
goldenkpg-0.1.0.dist-info/top_level.txt
goldenkpg-0.1.0.dist-info/RECORD
