Metadata-Version: 2.4
Name: goldenkpg
Version: 0.1.0
Summary: A CLI tool to generate Operating System algorithm templates.
Author: Code Architect
Classifier: Programming Language :: Python :: 3
Classifier: License :: OSI Approved :: MIT License
Classifier: Operating System :: OS Independent
Requires-Python: >=3.6
Dynamic: author
Dynamic: classifier
Dynamic: description
Dynamic: description-content-type
Dynamic: requires-python
Dynamic: summary
